README.md
setup.py
ecuapassdocs/__init__.py
ecuapassdocs.egg-info/PKG-INFO
ecuapassdocs.egg-info/SOURCES.txt
ecuapassdocs.egg-info/dependency_links.txt
ecuapassdocs.egg-info/requires.txt
ecuapassdocs.egg-info/top_level.txt
ecuapassdocs/info/__init__.py
ecuapassdocs/info/ecuapass_data.py
ecuapassdocs/info/ecuapass_extractor.py
ecuapassdocs/info/ecuapass_info.py
ecuapassdocs/info/ecuapass_info_cartaporte.py
ecuapassdocs/info/ecuapass_info_cartaporte_ALDIA.py
ecuapassdocs/info/ecuapass_info_cartaporte_BYZA.py
ecuapassdocs/info/ecuapass_info_cartaporte_LOGITRANS.py
ecuapassdocs/info/ecuapass_info_cartaporte_NTA.py
ecuapassdocs/info/ecuapass_info_declaracion.py
ecuapassdocs/info/ecuapass_info_manifiesto.py
ecuapassdocs/info/ecuapass_info_manifiesto_ALDIA.py
ecuapassdocs/info/ecuapass_info_manifiesto_BYZA.py
ecuapassdocs/info/ecuapass_info_manifiesto_LOGITRANS.py
ecuapassdocs/info/ecuapass_info_manifiesto_NTA.py
ecuapassdocs/info/ecuapass_utils.py
ecuapassdocs/info/resourceloader.py
ecuapassdocs/resources/__init__.py
ecuapassdocs/resources/data_cartaportes/__init__.py
ecuapassdocs/resources/data_cartaportes/ciudades-paises-colombia-ecuador.txt
ecuapassdocs/resources/data_cartaportes/ciudades_bolivia.txt
ecuapassdocs/resources/data_cartaportes/ciudades_colombia.txt
ecuapassdocs/resources/data_cartaportes/ciudades_ecuador.txt
ecuapassdocs/resources/data_cartaportes/ciudades_peru.txt
ecuapassdocs/resources/data_cartaportes/condiciones_pago.txt
ecuapassdocs/resources/data_cartaportes/condiciones_transporte.txt
ecuapassdocs/resources/data_cartaportes/depositos_cebaf.txt
ecuapassdocs/resources/data_cartaportes/depositos_huaquillas.txt
ecuapassdocs/resources/data_cartaportes/depositos_loja.txt
ecuapassdocs/resources/data_cartaportes/depositos_quito.txt
ecuapassdocs/resources/data_cartaportes/depositos_tulcan.txt
ecuapassdocs/resources/data_cartaportes/derivado.txt
ecuapassdocs/resources/data_cartaportes/distritos.txt
ecuapassdocs/resources/data_cartaportes/documentos.txt
ecuapassdocs/resources/data_cartaportes/empresa.txt
ecuapassdocs/resources/data_cartaportes/meses.txt
ecuapassdocs/resources/data_cartaportes/monedas.txt
