Metadata-Version: 2.1
Name: ecuapassdocs
Version: 0.861
Summary: Utils for creating PDFs, loading resources and extracting info from fields in ECUAPASS docs: cartaportes, manifiestos, declaraciones
Home-page: https://github.com/lgarreta/ecuapassdocs
Author: Luis Garreta
Author-email: lgarreta@gmail.com
License: UNKNOWN
Platform: UNKNOWN
